{"chunk_definitions":[{"row":12,"row_count":1,"visible":true,"expansion_state":0,"options":{"engine":"r","label":"setup","include":false},"document_id":"1CE19BA0","chunk_id":"csetup_chunk","chunk_label":"setup"},{"row":24,"row_count":1,"visible":true,"expansion_state":0,"options":{"engine":"r","label":"librerias","include":false},"document_id":"1CE19BA0","chunk_id":"cunh8f7suavby","chunk_label":"librerias"},{"row":42,"row_count":1,"visible":true,"expansion_state":0,"options":{"engine":"r","label":"unnamed-chunk-2"},"document_id":"1CE19BA0","chunk_id":"c6zbk7d0h8svt","chunk_label":"unnamed-chunk-1"},{"row":64,"row_count":1,"visible":true,"expansion_state":0,"options":{"engine":"r","label":"unnamed-chunk-3"},"document_id":"1CE19BA0","chunk_id":"c5qvf0wl753jy","chunk_label":"unnamed-chunk-2"},{"row":68,"row_count":1,"visible":true,"expansion_state":0,"options":{"engine":"r","label":"unnamed-chunk-4"},"document_id":"1CE19BA0","chunk_id":"c8k708oyyznyp","chunk_label":"unnamed-chunk-3"},{"row":72,"row_count":1,"visible":true,"expansion_state":0,"options":{"engine":"r","label":"agregar columana"},"document_id":"1CE19BA0","chunk_id":"cbokjgfpdza1z","chunk_label":"agregar columana"},{"row":124,"row_count":1,"visible":true,"expansion_state":0,"options":{"engine":"r","fig.width":10,"fig.height":7,"label":"unnamed-chunk-23"},"document_id":"1CE19BA0","chunk_id":"c5t9sxsk22om4","chunk_label":"unnamed-chunk-4"},{"row":129,"row_count":1,"visible":true,"expansion_state":0,"options":{"engine":"r","label":"unnamed-chunk-6"},"document_id":"1CE19BA0","chunk_id":"cpc72dymcq72y","chunk_label":"unnamed-chunk-5"},{"row":137,"row_count":1,"visible":true,"expansion_state":0,"options":{"engine":"r","label":"unnamed-chunk-7"},"document_id":"1CE19BA0","chunk_id":"cwhtgr6uowes9","chunk_label":"unnamed-chunk-6"},{"row":148,"row_count":1,"visible":true,"expansion_state":0,"options":{"engine":"r","fig.width":4,"fig.height":3,"label":"unnamed-chunk-22"},"document_id":"1CE19BA0","chunk_id":"ceidwxi8udwpm","chunk_label":"unnamed-chunk-7"},{"row":159,"row_count":1,"visible":true,"expansion_state":0,"options":{"engine":"r","label":"unnamed-chunk-9"},"document_id":"1CE19BA0","chunk_id":"cgvww2hdzkvm5","chunk_label":"unnamed-chunk-8"},{"row":172,"row_count":1,"visible":true,"expansion_state":0,"options":{"engine":"r","fig.width":12,"fig.height":5,"label":"unnamed-chunk-10"},"document_id":"1CE19BA0","chunk_id":"cw2lz0alst6hp","chunk_label":"unnamed-chunk-9"},{"row":181,"row_count":1,"visible":true,"expansion_state":0,"options":{"engine":"r","fig.width":4,"fig.height":3.5,"label":"unnamed-chunk-21"},"document_id":"1CE19BA0","chunk_id":"czrst0vyg93j7","chunk_label":"unnamed-chunk-10"},{"row":196,"row_count":1,"visible":true,"expansion_state":0,"options":{"engine":"r","label":"unnamed-chunk-12"},"document_id":"1CE19BA0","chunk_id":"cnc1ijj0b0ocu","chunk_label":"unnamed-chunk-11"},{"row":205,"row_count":1,"visible":true,"expansion_state":0,"options":{"engine":"r","label":"unnamed-chunk-13"},"document_id":"1CE19BA0","chunk_id":"cpsmp5wqvfw9t","chunk_label":"unnamed-chunk-12"},{"row":216,"row_count":1,"visible":true,"expansion_state":0,"options":{"engine":"r","fig.width":12,"fig.height":11,"label":"unnamed-chunk-14"},"document_id":"1CE19BA0","chunk_id":"cpudm82b0uogj","chunk_label":"unnamed-chunk-13"}],"doc_write_time":1685846976,"working_dir":null,"default_chunk_options":{"echo":false}}